style_repaint.py
image_style_repaint-0.1.2.dist-info/METADATA
image_style_repaint-0.1.2.dist-info/WHEEL
image_style_repaint-0.1.2.dist-info/entry_points.txt
image_style_repaint-0.1.2.dist-info/top_level.txt
image_style_repaint-0.1.2.dist-info/RECORD
