Metadata-Version: 2.2
Name: image-style-repaint
Version: 0.1.2
Summary: Generate styled image using bailian/wanx-style-repaint-v1
Requires-Python: >=3.10
Requires-Dist: python-dotenv>=1.0.1
Requires-Dist: requests>=2.32.3
